README.md
setup.py
messidge/__init__.py
messidge/loop.py
messidge.egg-info/PKG-INFO
messidge.egg-info/SOURCES.txt
messidge.egg-info/dependency_links.txt
messidge.egg-info/requires.txt
messidge.egg-info/top_level.txt
messidge/broker/__init__.py
messidge/broker/agent.py
messidge/broker/auth.py
messidge/broker/bases.py
messidge/broker/broker.py
messidge/broker/identity.py
messidge/broker/message.py
messidge/client/__init__.py
messidge/client/connection.py
messidge/client/message.py